LICENSE
MANIFEST.in
README.md
setup.py
a10sdk/__init__.py
a10sdk/version.py
a10sdk.egg-info/PKG-INFO
a10sdk.egg-info/SOURCES.txt
a10sdk.egg-info/dependency_links.txt
a10sdk.egg-info/top_level.txt
a10sdk/common/A10BaseClass.py
a10sdk/common/__init__.py
a10sdk/common/device_proxy.py
a10sdk/core/__init__.py
a10sdk/core/A10_copy/A10WW_copy.py
a10sdk/core/A10_copy/__init__.py
a10sdk/core/A10_file/A10WW_file.py
a10sdk/core/A10_file/__init__.py
a10sdk/core/A10_file/file_aflex.py
a10sdk/core/A10_file/file_aflex_oper.py
a10sdk/core/A10_file/file_auth_portal.py
a10sdk/core/A10_file/file_auth_portal_image.py
a10sdk/core/A10_file/file_auth_portal_image_oper.py
a10sdk/core/A10_file/file_auth_portal_oper.py
a10sdk/core/A10_file/file_auth_saml_idp.py
a10sdk/core/A10_file/file_auth_saml_idp_oper.py
a10sdk/core/A10_file/file_axdebug.py
a10sdk/core/A10_file/file_bw_list.py
a10sdk/core/A10_file/file_bw_list_oper.py
a10sdk/core/A10_file/file_ca_cert.py
a10sdk/core/A10_file/file_ca_cert_oper.py
a10sdk/core/A10_file/file_class_list.py
a10sdk/core/A10_file/file_class_list_oper.py
a10sdk/core/A10_file/file_debug_monitor.py
a10sdk/core/A10_file/file_dnssec_dnskey.py
a10sdk/core/A10_file/file_dnssec_dnskey_oper.py
a10sdk/core/A10_file/file_dnssec_ds.py
a10sdk/core/A10_file/file_dnssec_ds_oper.py
a10sdk/core/A10_file/file_geo_location_oper.py
a10sdk/core/A10_file/file_health_external.py
a10sdk/core/A10_file/file_health_external_oper.py
a10sdk/core/A10_file/file_health_postfile.py
a10sdk/core/A10_file/file_health_postfile_oper.py
a10sdk/core/A10_file/file_license.py
a10sdk/core/A10_file/file_license_oper.py
a10sdk/core/A10_file/file_local_uri_file.py
a10sdk/core/A10_file/file_local_uri_file_oper.py
a10sdk/core/A10_file/file_log_backup.py
a10sdk/core/A10_file/file_policy.py
a10sdk/core/A10_file/file_policy_oper.py
a10sdk/core/A10_file/file_ssl_cert.py
a10sdk/core/A10_file/file_ssl_cert_key.py
a10sdk/core/A10_file/file_ssl_cert_oper.py
a10sdk/core/A10_file/file_ssl_crl.py
a10sdk/core/A10_file/file_ssl_crl_oper.py
a10sdk/core/A10_file/file_ssl_key.py
a10sdk/core/A10_file/file_ssl_key_oper.py
