Metadata-Version: 1.1
Name: a10sdk
Version: 4.0.1.214
Summary: A10 Networks ACOS Python SDK
Home-page: https://github.com/a10networks/a10sdk-python
Author: A10 Networks
Author-email: support@a10networks.com
License: Apache
Keywords: a10 axapi acos adc slb load balancer
Platform: UNKNOWN
Classifier: License :: OSI Approved :: Apache Software License
Classifier: Operating System :: POSIX
Classifier: Programming Language :: Python
Classifier: Programming Language :: Python :: 2.6
Classifier: Programming Language :: Python :: 2.7
Classifier: Topic :: Internet
